g.py
setup.cfg
setup.py
blahblahblahblah3.egg-info/PKG-INFO
blahblahblahblah3.egg-info/SOURCES.txt
blahblahblahblah3.egg-info/dependency_links.txt
blahblahblahblah3.egg-info/pbr.json
blahblahblahblah3.egg-info/top_level.txt