Metadata-Version: 1.0
Name: blahblahblahblah3
Version: 13.13.13
Summary: A package to test packaging with
Home-page: UNKNOWN
Author: UNKNOWN
Author-email: UNKNOWN
License: UNKNOWN
Platform: UNKNOWN
